{
    "rescode": "200",
    "errInfo": "",
    "data": {
        "memberLevel": "微信会员",
        "room": {
            "roomId": "1",
            "roomName": "海景公寓",
            "roomRemain": "10",
            "purchaseAbility": "5",
            "roomImgGallery": [{
                "imgSrc": "api/img/room1.jpg"
            }, {
                "imgSrc": "api/img/room2.jpg"
            }],
            "roomFeatures": [
                { "name": "  WIFI  ", "icon": "  ion-wifi" },
                { "name": "  叫早  ", "icon": "  ion-android-alarm-clock" }
            ]
        },
        "hotel": {
            "hotelId": "1",
            "hotelName": "酒店名字一"
        },
        "priceList": [{
            "date":"1288323623006",
            "price":"100"
        }, {
            "date":"1289323623006",
            "price":"200"
        }, {
            "date":"1290323623006",
            "price":"300"
        }]
    }

}
